README.rst
setup.py
pybuilder_emr_plugin/__init__.py
pybuilder_emr_plugin/emr_tasks.py
pybuilder_emr_plugin/helpers.py
pybuilder_emr_plugin.egg-info/PKG-INFO
pybuilder_emr_plugin.egg-info/SOURCES.txt
pybuilder_emr_plugin.egg-info/dependency_links.txt
pybuilder_emr_plugin.egg-info/namespace_packages.txt
pybuilder_emr_plugin.egg-info/requires.txt
pybuilder_emr_plugin.egg-info/top_level.txt
pybuilder_emr_plugin.egg-info/zip-safe