Metadata-Version: 1.1
Name: pybuilder-emr-plugin
Version: 1.1.0
Summary: PyBuilder plugin to handle Amazon EMR functionality
Home-page: https://github.com/OberbaumConcept/pybuilder_emr_plugin.git
Author: Janne K. Olesen
Author-email: janne.olesen@oberbaum-concept.com
License: Apache
Platform: UNKNOWN
Classifier: Development Status :: 5 - Production/Stable
Classifier: Environment :: Console
Classifier: Intended Audience :: Developers
Classifier: Intended Audience :: System Administrators
Classifier: License :: OSI Approved :: Apache Software License
Classifier: Programming Language :: Python
Classifier: Operating System :: POSIX :: Linux
Classifier: Topic :: System :: Software Distribution
Classifier: Topic :: System :: Systems Administration
Classifier: Topic :: System :: Archiving :: Packaging
Classifier: Topic :: Utilities
